mosaik_multi_project/multi_project/__init__.py
mosaik_multi_project/multi_project/cli/__init__.py
mosaik_multi_project/multi_project/cli/main.py
mosaik_multi_project/multi_project/library/__init__.py
mosaik_multi_project/multi_project/library/get_command_line_arguments_module.py
mosaik_multi_project/multi_project/library/get_log_message_module.py
mosaik_multi_project/multi_project/library/list_operations_module.py
mosaik_multi_project/multi_project/library/load_project_aliases_module.py
mosaik_multi_project/multi_project/library/load_projects_from_configs_module.py
mosaik_multi_project/multi_project/library/parse_config.py
mosaik_multi_project/multi_project/library/setup_project.py
mosaik_multi_project/multi_project/library/strings.py
mosaik_multi_project/multi_project/util/paths.py
mosaik.Multi_Project-0.1.0rc20210825000703.dist-info/LICENSE.txt
mosaik.Multi_Project-0.1.0rc20210825000703.dist-info/METADATA
mosaik.Multi_Project-0.1.0rc20210825000703.dist-info/WHEEL
mosaik.Multi_Project-0.1.0rc20210825000703.dist-info/top_level.txt
mosaik.Multi_Project-0.1.0rc20210825000703.dist-info/RECORD
