Metadata-Version: 2.1
Name: mosaik.Multi-Project
Version: 0.1.0rc20210825000703
Summary: Manage multiple mosaik projects with using common tooling.
Home-page: https://gitlab.com/offis.energy/mosaik/mosaik.multi-project
Author: Bengt Lüers
Author-email: bengt.lueers@gmail.com
Maintainer: Bengt Lüers
Maintainer-email: bengt.lueers@gmail.com
License: UNKNOWN
Platform: UNKNOWN
Classifier: Development Status :: 5 - Production/Stable
Classifier: Intended Audience :: Science/Research
Classifier: License :: OSI Approved :: GNU Lesser General Public License v2 (LGPLv2)
Classifier: Natural Language :: English
Classifier: Operating System :: OS Independent
Classifier: Programming Language :: Python
Classifier: Programming Language :: Python :: 3
Classifier: Programming Language :: Python :: 3.7
Classifier: Programming Language :: Python :: 3.8
Classifier: Programming Language :: Python :: 3.9
Classifier: Topic :: Scientific/Engineering
Classifier: Topic :: Software Development :: Libraries :: Python Modules
License-File: LICENSE.txt
Requires-Dist: click (>=7.0)
